shapley_value/__init__.py
shapley_value/calculator.py
shapley_value/combinations.py
shapley_value/framework.py
shapley_value/py.typed
shapley_value/utils.py
shapley_value-0.0.5.dist-info/licenses/LICENSE
shapley_value-0.0.5.dist-info/METADATA
shapley_value-0.0.5.dist-info/WHEEL
shapley_value-0.0.5.dist-info/top_level.txt
shapley_value-0.0.5.dist-info/RECORD
