Metadata-Version: 2.4
Name: shapley-value
Version: 0.0.5
Summary: A comprehensive Python package for calculating Shapley values in cooperative game theory
Home-page: https://github.com/Bowenislandsong/shapley-value
Author: Bowen Song
Author-email: Bowen Song <bowenson@example.com>
Maintainer: Bowen Song
Maintainer-email: Bowen Song <bowenson@example.com>
License: MIT
Project-URL: Homepage, https://github.com/Bowenislandsong/shapley-value
Project-URL: Source, https://github.com/Bowenislandsong/shapley-value
Project-URL: Bug Reports, https://github.com/Bowenislandsong/shapley-value/issues
Project-URL: Documentation, https://github.com/Bowenislandsong/shapley-value#readme
Project-URL: Examples, https://github.com/Bowenislandsong/shapley-value/tree/main/examples
Project-URL: Changelog, https://github.com/Bowenislandsong/shapley-value/blob/main/CHANGELOG.md
Project-URL: Author, https://bowenislandsong.github.io/#/personal
Keywords: shapley,shapley-value,game-theory,cooperative-games,fair-allocation,coalition,marginal-contribution,economics,mathematics,optimization,machine-learning,feature-importance,explainable-ai,xai
Platform: any
Classifier: Development Status :: 5 - Production/Stable
Classifier: Intended Audience :: Developers
Classifier: Intended Audience :: Science/Research
Classifier: Intended Audience :: Education
Classifier: Intended Audience :: Financial and Insurance Industry
Classifier: Topic :: Scientific/Engineering :: Mathematics
Classifier: Topic :: Scientific/Engineering :: Artificial Intelligence
Classifier: Topic :: Software Development :: Libraries :: Python Modules
Classifier: Topic :: Office/Business :: Financial
Classifier: License :: OSI Approved :: MIT License
Classifier: Programming Language :: Python :: 3
Classifier: Programming Language :: Python :: 3.7
Classifier: Programming Language :: Python :: 3.8
Classifier: Programming Language :: Python :: 3.9
Classifier: Programming Language :: Python :: 3.10
Classifier: Programming Language :: Python :: 3.11
Classifier: Programming Language :: Python :: 3.12
Classifier: Operating System :: OS Independent
Classifier: Environment :: Console
Classifier: Environment :: Web Environment
Classifier: Natural Language :: English
Requires-Python: >=3.7
License-File: LICENSE
Requires-Dist: joblib>=1.0.0
Provides-Extra: dev
Requires-Dist: pytest>=6.0; extra == "dev"
Requires-Dist: pytest-cov; extra == "dev"
Requires-Dist: black; extra == "dev"
Requires-Dist: flake8; extra == "dev"
Requires-Dist: mypy; extra == "dev"
Requires-Dist: pre-commit; extra == "dev"
Provides-Extra: examples
Requires-Dist: pandas>=1.0.0; extra == "examples"
Requires-Dist: numpy>=1.18.0; extra == "examples"
Provides-Extra: performance
Requires-Dist: pandas>=1.0.0; extra == "performance"
Requires-Dist: psutil; extra == "performance"
Provides-Extra: all
Requires-Dist: shapley-value[dev,examples,performance]; extra == "all"
Dynamic: author
Dynamic: home-page
Dynamic: license-file
Dynamic: maintainer
Dynamic: platform
Dynamic: requires-python
